scgeno/__init__.py
scgeno/main.py
scgeno-0.1.5.dist-info/METADATA
scgeno-0.1.5.dist-info/WHEEL
scgeno-0.1.5.dist-info/entry_points.txt
scgeno-0.1.5.dist-info/licenses/LICENSE.md
scgeno-0.1.5.dist-info/RECORD
