Metadata-Version: 2.4
Name: scgeno
Version: 0.1.5
Summary: Single-cell genotyping using Hidden Markov Model
Project-URL: Repository, https://github.com/RosariaTornisiello/Genotype_HMM
Author-email: Rosaria Tornisiello <rosaria.tornisiello@hpi.de>
License: MIT
License-File: LICENSE.md
Classifier: Development Status :: 3 - Alpha
Classifier: Intended Audience :: Science/Research
Classifier: License :: OSI Approved :: MIT License
Classifier: Programming Language :: Python :: 3.10
Requires-Python: >=3.10
Requires-Dist: hmmlearn>=0.3.3
Requires-Dist: natsort>=8.4.0
Requires-Dist: numpy>=1.22
Requires-Dist: pandas>=2.2.3
Requires-Dist: scanpy>=1.10.3
Requires-Dist: seaborn>=0.13.2
Requires-Dist: tqdm>=4.67.1
